trans.py
trans_rebuild-2.1.0b0.dist-info/LICENSE
trans_rebuild-2.1.0b0.dist-info/METADATA
trans_rebuild-2.1.0b0.dist-info/WHEEL
trans_rebuild-2.1.0b0.dist-info/top_level.txt
trans_rebuild-2.1.0b0.dist-info/RECORD
